Eli_SN_Version_Compare/__init__.py
Eli_SN_Version_Compare/function.py
Elizabeth_SN-1.1.0.dist-info/METADATA
Elizabeth_SN-1.1.0.dist-info/WHEEL
Elizabeth_SN-1.1.0.dist-info/top_level.txt
Elizabeth_SN-1.1.0.dist-info/RECORD
