Metadata-Version: 2.1
Name: Elizabeth-SN
Version: 1.1.0
Summary: Makes a Version Comparison 
Author: Elizabeth J Martinez A
License: MIT
Requires-Dist: numpy
